{
  "default": {
    "database": {
      "host": "localhost",
      "user": "jubilant",
      "password": "jubilant",
      "database": "jubilant"
    },
    "server": {
      "port": 8383
    },
    "email": {
      "serviceAccount": "no-reply@getodk.org",
      "transport": "json"
    },
    "xlsform": {
      "host": "localhost",
      "port": 5000
    },
    "enketo": {
      "url": "http://localhost:8005/-",
      "apiKey": "enketorules"
    },
    "env": {
      "domain": "http://localhost:8989",
      "sysadminAccount": "no-reply@getodk.org"
    },
    "external": {
      "google": {
        "clientId": "660095633112-h7bhsjenhp1agd0c4v3cmqk6bccgkdu0.apps.googleusercontent.com",
        "clientSecret": "lzu2vK1NFqqd6Y5HiN-7ByvE"
      },
      "sentry": {},
      "analytics": {
        "url": "https://data.getodk.cloud/v1/key/eOZ7S4bzyUW!g1PF6dIXsnSqktRuewzLTpmc6ipBtRq$LDfIMTUKswCexvE0UwJ9/projects/1/submission",
        "formId": "odk-analytics",
        "version": "2022.11.29.01"
      }
    }
  },
  "test": {
    "database": {
      "host": "localhost",
      "user": "jubilant",
      "password": "jubilant",
      "database": "jubilant_test"
    },
    "email": {
      "serviceAccount": "no-reply@getodk.org",
      "transport": "json",
      "transportOpts": { "newline": "unix" }
    }
  }
}

